miniquant/__init__.py
miniquant/_version.py
miniquant/app.py
miniquant/epif.py
miniquant/harp.py
miniquant/mock_harp.py
miniquant/tests_hw/__init__.py
miniquant/tests_hw/harp_test.py
miniquant/tests_hw/harp_test_quirked.py
miniquant-0.3.4.dist-info/LICENSE
miniquant-0.3.4.dist-info/METADATA
miniquant-0.3.4.dist-info/WHEEL
miniquant-0.3.4.dist-info/top_level.txt
miniquant-0.3.4.dist-info/RECORD
