Metadata-Version: 2.1
Name: miniquant
Version: 0.3.4
Summary: Python interface for the Harp class of PicoQuant\'s time interval analysers and photon counters
Author: Florin Boariu
Author-email: florin.pt@rootshell.ro
Project-URL: Source Code, https://gitlab.com/codedump2/miniquant/
Project-URL: Bug Tracker, https://gitlab.com/codedump2/miniquant/-/issues
Classifier: Programming Language :: Python :: 3
Classifier: License :: OSI Approved :: GNU General Public License v3 or later (GPLv3+)
Classifier: Operating System :: POSIX :: Linux
Classifier: Development Status :: 2 - Pre-Alpha
Classifier: Environment :: Console
Classifier: Intended Audience :: Science/Research
Classifier: Topic :: Scientific/Engineering
License-File: LICENSE
Requires-Dist: numpy
Requires-Dist: libusb1
Provides-Extra: test
Requires-Dist: pytest ; extra == 'test'
Requires-Dist: pytest-cov ; extra == 'test'
